rigol1000z/__init__.py
rigol1000z/rigol1000z.py
Rigol1000z-0.2.2.dist-info/LICENSE
Rigol1000z-0.2.2.dist-info/METADATA
Rigol1000z-0.2.2.dist-info/WHEEL
Rigol1000z-0.2.2.dist-info/top_level.txt
Rigol1000z-0.2.2.dist-info/RECORD
