Metadata-Version: 2.1
Name: Rigol1000z
Version: 0.2.2
Summary: Python VISA (USB and Ethernet) library to control Rigol DS1000z series oscilloscopes.
Home-page: https://github.com/jeanyvesb9/Rigol1000z
Author: Jean Yves Beaucamp (@jeanyvesb9), @jtambasco
Author-email: jeanyvesb9@me.com
License: UNKNOWN
Platform: UNKNOWN
